summation/__init__.py
summation/summation.py
testingaddnumbers-0.0.1.dist-info/METADATA
testingaddnumbers-0.0.1.dist-info/WHEEL
testingaddnumbers-0.0.1.dist-info/top_level.txt
testingaddnumbers-0.0.1.dist-info/RECORD
