Metadata-Version: 2.1
Name: testingaddnumbers
Version: 0.0.1
Summary: A basis sum function
Author: Mohd Sabir
Author-email: sabir9202@gmail.com
